<?xml version="1.0" encoding="UTF-8"?>
<data>
	<node>
		<name><![CDATA[TABULO_Декоративні_ламелі]]></name>
		<type><![CDATA[variable]]></type>
		<sku><![CDATA[TABULO-LAMELI]]></sku>
		<parentsku><![CDATA[]]></parentsku>
		<attributepa_color><![CDATA[]]></attributepa_color>
		<attributepa_series><![CDATA[]]></attributepa_series>
		<images><![CDATA[]]></images>
		<_woodmart_swatch_color><![CDATA[]]></_woodmart_swatch_color>
		<managestock><![CDATA[]]></managestock>
		<stockquantity><![CDATA[]]></stockquantity>
		<stockstatus><![CDATA[instock]]></stockstatus>
		<regularprice><![CDATA[]]></regularprice>
		<category><![CDATA[]]></category>
	</node>
	<node>
		<name><![CDATA[STONEHENGE ПЕРЛИНА-БАЛТИКИ]]></name>
		<type><![CDATA[variation]]></type>
		<sku><![CDATA[ST-ПЕРЛИНА-БАЛТИКИ]]></sku>
		<parentsku><![CDATA[TABULO-LAMELI]]></parentsku>
		<attributepa_color><![CDATA[перлина-балтики]]></attributepa_color>
		<attributepa_series><![CDATA[Other]]></attributepa_series>
		<images><![CDATA[https://kosbud.com.pl/wp-content/uploads/2019/10/struktury-Perła-Bałtyku-struktura-z-fugą-gotowe.png]]></images>
		<_woodmart_swatch_color><![CDATA[#000000]]></_woodmart_swatch_color>
		<managestock><![CDATA[yes]]></managestock>
		<stockquantity><![CDATA[10]]></stockquantity>
		<stockstatus><![CDATA[instock]]></stockstatus>
		<regularprice><![CDATA[0]]></regularprice>
		<category><![CDATA[Перлина Балтики]]></category>
	</node>
	<node>
		<name><![CDATA[STONEHENGE СВІТЛИЙ-ДУБ]]></name>
		<type><![CDATA[variation]]></type>
		<sku><![CDATA[ST-СВІТЛИЙ-ДУБ]]></sku>
		<parentsku><![CDATA[TABULO-LAMELI]]></parentsku>
		<attributepa_color><![CDATA[світлий-дуб]]></attributepa_color>
		<attributepa_series><![CDATA[Other]]></attributepa_series>
		<images><![CDATA[https://kosbud.com.pl/wp-content/uploads/2019/10/Jasny-Dąb-korekta-łączeń-i-kolorów.png]]></images>
		<_woodmart_swatch_color><![CDATA[#000000]]></_woodmart_swatch_color>
		<managestock><![CDATA[yes]]></managestock>
		<stockquantity><![CDATA[10]]></stockquantity>
		<stockstatus><![CDATA[instock]]></stockstatus>
		<regularprice><![CDATA[0]]></regularprice>
		<category><![CDATA[Світлий дуб]]></category>
	</node>
	<node>
		<name><![CDATA[STONEHENGE ЗОЛОТИЙ-ДУБ]]></name>
		<type><![CDATA[variation]]></type>
		<sku><![CDATA[ST-ЗОЛОТИЙ-ДУБ]]></sku>
		<parentsku><![CDATA[TABULO-LAMELI]]></parentsku>
		<attributepa_color><![CDATA[золотий-дуб]]></attributepa_color>
		<attributepa_series><![CDATA[Other]]></attributepa_series>
		<images><![CDATA[https://kosbud.com.pl/wp-content/uploads/2019/10/struktury-złoty-dąb-bez-korekty-kolorów-gotowe.png]]></images>
		<_woodmart_swatch_color><![CDATA[#000000]]></_woodmart_swatch_color>
		<managestock><![CDATA[yes]]></managestock>
		<stockquantity><![CDATA[10]]></stockquantity>
		<stockstatus><![CDATA[instock]]></stockstatus>
		<regularprice><![CDATA[0]]></regularprice>
		<category><![CDATA[Золотий дуб]]></category>
	</node>
	<node>
		<name><![CDATA[STONEHENGE ВІНЧЕСТЕР]]></name>
		<type><![CDATA[variation]]></type>
		<sku><![CDATA[ST-ВІНЧЕСТЕР]]></sku>
		<parentsku><![CDATA[TABULO-LAMELI]]></parentsku>
		<attributepa_color><![CDATA[вінчестер]]></attributepa_color>
		<attributepa_series><![CDATA[Other]]></attributepa_series>
		<images><![CDATA[https://kosbud.com.pl/wp-content/uploads/2019/10/struktury-Winchester-gotowe.png]]></images>
		<_woodmart_swatch_color><![CDATA[#000000]]></_woodmart_swatch_color>
		<managestock><![CDATA[yes]]></managestock>
		<stockquantity><![CDATA[10]]></stockquantity>
		<stockstatus><![CDATA[instock]]></stockstatus>
		<regularprice><![CDATA[0]]></regularprice>
		<category><![CDATA[Вінчестер]]></category>
	</node>
	<node>
		<name><![CDATA[STONEHENGE ТЕМНИЙ-ГОРІХ]]></name>
		<type><![CDATA[variation]]></type>
		<sku><![CDATA[ST-ТЕМНИЙ-ГОРІХ]]></sku>
		<parentsku><![CDATA[TABULO-LAMELI]]></parentsku>
		<attributepa_color><![CDATA[темний-горіх]]></attributepa_color>
		<attributepa_series><![CDATA[Other]]></attributepa_series>
		<images><![CDATA[https://kosbud.com.pl/wp-content/uploads/2019/10/struktury-Ciemny-Orzech-z-fugą.png]]></images>
		<_woodmart_swatch_color><![CDATA[#000000]]></_woodmart_swatch_color>
		<managestock><![CDATA[yes]]></managestock>
		<stockquantity><![CDATA[10]]></stockquantity>
		<stockstatus><![CDATA[instock]]></stockstatus>
		<regularprice><![CDATA[0]]></regularprice>
		<category><![CDATA[Темний горіх]]></category>
	</node>
	<node>
		<name><![CDATA[STONEHENGE ЧЕРВОНЕ-ДЕРЕВО]]></name>
		<type><![CDATA[variation]]></type>
		<sku><![CDATA[ST-ЧЕРВОНЕ-ДЕРЕВО]]></sku>
		<parentsku><![CDATA[TABULO-LAMELI]]></parentsku>
		<attributepa_color><![CDATA[червоне-дерево]]></attributepa_color>
		<attributepa_series><![CDATA[Other]]></attributepa_series>
		<images><![CDATA[https://kosbud.com.pl/wp-content/uploads/2019/10/struktury-Mahoń-korekta-koloru-z-fugą-3-wybrane.png]]></images>
		<_woodmart_swatch_color><![CDATA[#000000]]></_woodmart_swatch_color>
		<managestock><![CDATA[yes]]></managestock>
		<stockquantity><![CDATA[10]]></stockquantity>
		<stockstatus><![CDATA[instock]]></stockstatus>
		<regularprice><![CDATA[0]]></regularprice>
		<category><![CDATA[Червоне дерево]]></category>
	</node>
	<node>
		<name><![CDATA[STONEHENGE ГРАФІТ]]></name>
		<type><![CDATA[variation]]></type>
		<sku><![CDATA[ST-ГРАФІТ]]></sku>
		<parentsku><![CDATA[TABULO-LAMELI]]></parentsku>
		<attributepa_color><![CDATA[графіт]]></attributepa_color>
		<attributepa_series><![CDATA[Other]]></attributepa_series>
		<images><![CDATA[https://kosbud.com.pl/wp-content/uploads/2019/10/struktury-Grafit-GOTOWY-kolor-z-fugą.png]]></images>
		<_woodmart_swatch_color><![CDATA[#000000]]></_woodmart_swatch_color>
		<managestock><![CDATA[yes]]></managestock>
		<stockquantity><![CDATA[10]]></stockquantity>
		<stockstatus><![CDATA[instock]]></stockstatus>
		<regularprice><![CDATA[0]]></regularprice>
		<category><![CDATA[Графіт]]></category>
	</node>
	<node>
		<name><![CDATA[STONEHENGE ВЕНГЕ]]></name>
		<type><![CDATA[variation]]></type>
		<sku><![CDATA[ST-ВЕНГЕ]]></sku>
		<parentsku><![CDATA[TABULO-LAMELI]]></parentsku>
		<attributepa_color><![CDATA[венге]]></attributepa_color>
		<attributepa_series><![CDATA[Other]]></attributepa_series>
		<images><![CDATA[https://kosbud.com.pl/wp-content/uploads/2019/10/struktury-Venge-z-fugą-gotowa.png]]></images>
		<_woodmart_swatch_color><![CDATA[#000000]]></_woodmart_swatch_color>
		<managestock><![CDATA[yes]]></managestock>
		<stockquantity><![CDATA[10]]></stockquantity>
		<stockstatus><![CDATA[instock]]></stockstatus>
		<regularprice><![CDATA[0]]></regularprice>
		<category><![CDATA[Венге]]></category>
	</node>
</data>
