[
"<!-- wp:wd\/container {\"blockId\":\"dd4080b9-553a-4d03-b4fe-115a0383f7cd\",\"direction\":\"row\",\"justify\":\"space-between\",\"wrap\":\"wrap\",\"rowGap\":\"10\",\"paddingBottom\":\"10\",\"marginTop\":\"-25\",\"borderType\":\"solid\",\"borderColorCode\":\"rgba(0,0,0,0.11)\",\"borderWidthBottom\":\"1\"} -->\n<div id=\"wd-dd4080b9\" class=\"wp-block-wd-container wd-dir-row\"><!-- wp:wd\/woo-breadcrumbs {\"blockId\":\"2db2bcd7-0eb8-4dd9-bc75-a7f42290108f\",\"nowrapMd\":true} \/-->\n\n<!-- wp:wd\/sp-navigation {\"blockId\":\"4098426e-3dc9-4dec-8eba-dfd9fb51bd46\"} \/--><\/div>\n<!-- \/wp:wd\/container -->\n\n<!-- wp:wd\/row {\"blockId\":\"8c863711-be0b-4599-962e-c1888f3b3c54\",\"columnsGap\":60,\"marginBottom\":\"60\",\"columnsGapTablet\":30,\"marginBottomTablet\":\"40\"} -->\n<div id=\"wd-8c863711\" class=\"wp-block-wd-row\"><!-- wp:wd\/column {\"blockId\":\"2c2ec030-6eb9-439a-9eba-b9687bd2c640\",\"adjacentCount\":2} -->\n<div id=\"wd-2c2ec030\" class=\"wp-block-wd-column\"><!-- wp:wd\/sp-gallery {\"blockId\":\"f7a77697-f299-4ac7-9c53-4239f82be981\"} \/--><\/div>\n<!-- \/wp:wd\/column -->\n\n<!-- wp:wd\/column {\"blockId\":\"a9904e09-399d-4eb4-b805-061542f43286\",\"adjacentCount\":2} -->\n<div id=\"wd-a9904e09\" class=\"wp-block-wd-column\"><!-- wp:wd\/woo-notices {\"blockId\":\"dbc50c5a-a923-4824-9270-e9da97ce77e5\"} \/-->\n\n<!-- wp:wd\/container {\"blockId\":\"2de8d68a-8a55-4bce-b669-4c3451bc0208\",\"direction\":\"row\",\"justify\":\"space-between\",\"directionTablet\":\"column\"} -->\n<div id=\"wd-2de8d68a\" class=\"wp-block-wd-container wd-dir-row wd-dir-col-md\"><!-- wp:wd\/sp-title {\"blockId\":\"5c67a556-5231-4cb2-a886-1289d2d1c3a1\",\"tpFontSize\":\"34\",\"tpFontVariant\":\"800\",\"tpFontWeight\":\"800\",\"displayWidth\":\"\",\"customWidth\":\"70\",\"tpFontSizeTablet\":\"24\",\"customWidthUnits\":\"%\",\"customWidthUnitsTablet\":\"%\"} \/-->\n\n<!-- wp:wd\/sp-brands {\"blockId\":\"9f306d77-ef0a-4c19-881b-9405f0cdf924\",\"title\":false,\"style\":\"shadow\",\"imageWidth\":80,\"flexSize\":\"none\",\"displayWidth\":\"\",\"imageWidthTablet\":60} \/--><\/div>\n<!-- \/wp:wd\/container -->\n\n<!-- wp:wd\/sp-meta {\"blockId\":\"8c2e68e4-59bb-4aaa-a1b9-22965467dfb6\",\"showCategories\":false,\"showTags\":false} \/-->\n\n<!-- wp:wd\/sp-rating {\"blockId\":\"1ff9e6d1-df3f-42c2-bc1f-d139250eeee1\"} \/-->\n\n<!-- wp:wd\/sp-price {\"blockId\":\"a0b1ce08-0c2d-4349-a1a5-decc73bfd3a2\",\"mainPriceTpFontSize\":\"28\",\"mainPriceTpFontSizeTablet\":\"18\"} \/-->\n\n<!-- wp:wd\/sp-countdown {\"blockId\":\"b4c5cf0f-0d13-4682-9e03-5aa161578ae3\"} \/-->\n\n<!-- wp:wd\/sp-stock-progress-bar {\"blockId\":\"1657cdc8-ac99-4b98-a403-675fad7e1a06\"} \/-->\n\n<!-- wp:wd\/woo-shipping-progress-bar {\"blockId\":\"08b5052f-90ff-4700-8094-7b88bf3c52ea\",\"paddingTop\":\"20\",\"paddingRight\":\"20\",\"paddingBottom\":\"20\",\"paddingLeft\":\"20\",\"paddingLock\":true,\"borderType\":\"dashed\",\"borderColorCode\":\"rgba(0,0,0,0.11)\",\"borderWidth\":\"2\",\"borderWidthTop\":\"2\",\"borderWidthRight\":\"2\",\"borderWidthBottom\":\"2\",\"borderWidthLeft\":\"2\",\"borderWidthLock\":true} \/-->\n\n<!-- wp:wd\/sp-linked-variations {\"blockId\":\"7fcd6e92-a675-449f-95f2-2f12bebba729\"} \/-->\n\n<!-- wp:wd\/container {\"blockId\":\"1c4cecd4-3d90-4fe3-ae4a-6bb36b96fc38\",\"colGap\":\"0\",\"rowGap\":\"0\",\"paddingLock\":true,\"borderType\":\"solid\",\"borderColorCode\":\"rgba(0,0,0,0.11)\",\"borderWidth\":\"1\",\"borderWidthTop\":\"1\",\"borderWidthRight\":\"1\",\"borderWidthBottom\":\"1\",\"borderWidthLeft\":\"1\",\"borderWidthLock\":true} -->\n<div id=\"wd-1c4cecd4\" class=\"wp-block-wd-container wd-dir-col\"><!-- wp:wd\/sp-add-to-cart {\"blockId\":\"aca9f26b-dba2-4760-948a-657bfdbb2a83\",\"paddingTop\":\"20\",\"paddingRight\":\"20\",\"paddingBottom\":\"20\",\"paddingLeft\":\"20\",\"paddingLock\":true} \/-->\n\n<!-- wp:wd\/container {\"blockId\":\"eaeb211e-752d-4b5e-9474-8d4294273af6\",\"direction\":\"row\",\"paddingTop\":\"20\",\"paddingRight\":\"20\",\"paddingBottom\":\"20\",\"paddingLeft\":\"20\",\"paddingLock\":true,\"borderType\":\"solid\",\"borderColorCode\":\"rgba(0,0,0,0.11)\",\"borderWidthTop\":\"1\",\"borderWidthLock\":false} -->\n<div id=\"wd-eaeb211e\" class=\"wp-block-wd-container wd-dir-row\"><!-- wp:wd\/sp-wishlist-btn {\"blockId\":\"af9ef7a6-38a9-4a37-a027-e9e56c4be40f\",\"paddingRight\":\"20\",\"borderType\":\"solid\",\"borderColorCode\":\"rgba(16,16,16,0.1)\",\"borderWidthRight\":\"1\"} \/-->\n\n<!-- wp:wd\/sp-compare-btn {\"blockId\":\"ce553253-13e6-4c51-a0ee-a971281a1172\"} \/--><\/div>\n<!-- \/wp:wd\/container --><\/div>\n<!-- \/wp:wd\/container -->\n\n<!-- wp:wd\/woo-hook {\"blockId\":\"671ece08-139a-41d7-b6b6-878c72425abc\",\"hook\":\"woocommerce_single_product_summary\",\"cleanActions\":true} \/-->\n\n<!-- wp:wd\/sp-visitor-counter {\"blockId\":\"c933c036-8553-42e6-a7be-e5f3df7223f0\",\"style\":\"with-bg\"} \/-->\n\n<!-- wp:wd\/row {\"blockId\":\"4a0b9a97-20c8-4015-ba4a-6d7b85ba8454\"} -->\n<div id=\"wd-4a0b9a97\" class=\"wp-block-wd-row\"><!-- wp:wd\/column {\"blockId\":\"42c68e38-c38f-4d2c-ac2c-98c8eea00582\",\"adjacentCount\":4,\"adjacentCountTablet\":3,\"adjacentCountMobile\":2,\"colWidthTablet\":33,\"colWidthMobile\":50} -->\n<div id=\"wd-42c68e38\" class=\"wp-block-wd-column\"><!-- wp:wd\/infobox {\"blockId\":\"5bb238ec-c883-4dad-b1f5-715160c0156b\",\"align\":\"center\"} -->\n<div id=\"wd-5bb238ec\" class=\"wp-block-wd-infobox wd-hover-parent wd-align wd-icon-top\"><!-- wp:wd\/icon {\"blockId\":\"7099a68d-edb2-4a07-8965-52cdc1936220\",\"image\":{\"id\":382,\"url\":\"http:\/\/dummy.xtemos.com\/woodmart2\/megamarket-gutenberg\/wp-content\/uploads\/sites\/25\/2024\/07\/product-delivery.svg\"},\"width\":\"32\"} -->\n<div id=\"wd-7099a68d\" class=\"wp-block-wd-icon\"><img class=\"wp-image-382\" src=\"http:\/\/dummy.xtemos.com\/woodmart2\/megamarket-gutenberg\/wp-content\/uploads\/sites\/25\/2024\/07\/product-delivery.svg\" alt=\"\" \/><\/div>\n<!-- \/wp:wd\/icon -->\n\n<!-- wp:wd\/container {\"blockId\":\"66cd4766-287d-4bda-ad90-b3dd0ac2f1da\",\"metadata\":{\"name\":\"Infobox content\"}} -->\n<div id=\"wd-66cd4766\" class=\"wp-block-wd-container wd-dir-col\"><!-- wp:wd\/title {\"blockId\":\"5df483d4-1555-4a8e-9b5d-417a42f543f3\",\"content\":\"Fast Shipping\",\"tpFontSize\":\"16\"} -->\n<h2 id=\"wd-5df483d4\" class=\"wp-block-wd-title title\">Fast Shipping<\/h2>\n<!-- \/wp:wd\/title -->\n\n<!-- wp:wd\/paragraph {\"blockId\":\"5a3d136b-8abe-4621-84c7-a79ee6da77d2\",\"tpFontSize\":\"14\"} -->\n<p id=\"wd-5a3d136b\" class=\"wp-block-wd-paragraph\">Carrier information<\/p>\n<!-- \/wp:wd\/paragraph --><\/div>\n<!-- \/wp:wd\/container --><\/div>\n<!-- \/wp:wd\/infobox --><\/div>\n<!-- \/wp:wd\/column -->\n\n<!-- wp:wd\/column {\"blockId\":\"acafc696-5b17-498b-b7e7-5f7295a19a92\",\"adjacentCount\":4,\"adjacentCountTablet\":3,\"adjacentCountMobile\":2,\"colWidthTablet\":33,\"colWidthMobile\":50} -->\n<div id=\"wd-acafc696\" class=\"wp-block-wd-column\"><!-- wp:wd\/infobox {\"blockId\":\"21bb3382-ce17-4a93-a9b6-a43b5c05257e\",\"align\":\"center\"} -->\n<div id=\"wd-21bb3382\" class=\"wp-block-wd-infobox wd-hover-parent wd-align wd-icon-top\"><!-- wp:wd\/icon {\"blockId\":\"f0e213ff-abe0-46e5-8637-250b5562e52a\",\"image\":{\"id\":381,\"url\":\"http:\/\/dummy.xtemos.com\/woodmart2\/megamarket-gutenberg\/wp-content\/uploads\/sites\/25\/2024\/07\/product-meny-products.svg\"},\"width\":\"32\"} -->\n<div id=\"wd-f0e213ff\" class=\"wp-block-wd-icon\"><img class=\"wp-image-381\" src=\"http:\/\/dummy.xtemos.com\/woodmart2\/megamarket-gutenberg\/wp-content\/uploads\/sites\/25\/2024\/07\/product-meny-products.svg\" alt=\"\" \/><\/div>\n<!-- \/wp:wd\/icon -->\n\n<!-- wp:wd\/container {\"blockId\":\"09bf32d0-43db-45da-b66f-32846680d9ba\",\"metadata\":{\"name\":\"Infobox content\"}} -->\n<div id=\"wd-09bf32d0\" class=\"wp-block-wd-container wd-dir-col\"><!-- wp:wd\/title {\"blockId\":\"0b3d1c74-5103-4ab3-8319-92d1be24e431\",\"content\":\"20k products\",\"tpFontSize\":\"16\"} -->\n<h2 id=\"wd-0b3d1c74\" class=\"wp-block-wd-title title\">20k products<\/h2>\n<!-- \/wp:wd\/title -->\n\n<!-- wp:wd\/paragraph {\"blockId\":\"0826aa94-b246-4917-ba45-1329df9c9a9c\",\"tpFontSize\":\"14\"} -->\n<p id=\"wd-0826aa94\" class=\"wp-block-wd-paragraph\">Payment methods<\/p>\n<!-- \/wp:wd\/paragraph --><\/div>\n<!-- \/wp:wd\/container --><\/div>\n<!-- \/wp:wd\/infobox --><\/div>\n<!-- \/wp:wd\/column -->\n\n<!-- wp:wd\/column {\"blockId\":\"2daf874a-1db6-41ad-849a-f187178ef13c\",\"adjacentCount\":4,\"adjacentCountTablet\":3,\"adjacentCountMobile\":2,\"colWidthTablet\":33,\"colWidthMobile\":50} -->\n<div id=\"wd-2daf874a\" class=\"wp-block-wd-column\"><!-- wp:wd\/infobox {\"blockId\":\"1aa8a213-7ce4-48db-8014-80b0a4657772\",\"align\":\"center\"} -->\n<div id=\"wd-1aa8a213\" class=\"wp-block-wd-infobox wd-hover-parent wd-align wd-icon-top\"><!-- wp:wd\/icon {\"blockId\":\"a087739f-4888-4f8a-bd20-faee8de869e7\",\"image\":{\"id\":379,\"url\":\"http:\/\/dummy.xtemos.com\/woodmart2\/megamarket-gutenberg\/wp-content\/uploads\/sites\/25\/2024\/07\/product-support.svg\"},\"width\":\"32\"} -->\n<div id=\"wd-a087739f\" class=\"wp-block-wd-icon\"><img class=\"wp-image-379\" src=\"http:\/\/dummy.xtemos.com\/woodmart2\/megamarket-gutenberg\/wp-content\/uploads\/sites\/25\/2024\/07\/product-support.svg\" alt=\"\" \/><\/div>\n<!-- \/wp:wd\/icon -->\n\n<!-- wp:wd\/container {\"blockId\":\"71bc4b70-06be-4e77-adc4-efabbfccb3df\",\"metadata\":{\"name\":\"Infobox content\"}} -->\n<div id=\"wd-71bc4b70\" class=\"wp-block-wd-container wd-dir-col\"><!-- wp:wd\/title {\"blockId\":\"79e7c468-0baf-4bc3-8d63-d9995d7fd172\",\"content\":\"24\/7 Support\",\"tpFontSize\":\"16\"} -->\n<h2 id=\"wd-79e7c468\" class=\"wp-block-wd-title title\">24\/7 Support<\/h2>\n<!-- \/wp:wd\/title -->\n\n<!-- wp:wd\/paragraph {\"blockId\":\"1bdc8f50-ed36-4c6d-9675-c9b368e6c4dc\",\"tpFontSize\":\"14\"} -->\n<p id=\"wd-1bdc8f50\" class=\"wp-block-wd-paragraph\">Unlimited help desk<\/p>\n<!-- \/wp:wd\/paragraph --><\/div>\n<!-- \/wp:wd\/container --><\/div>\n<!-- \/wp:wd\/infobox --><\/div>\n<!-- \/wp:wd\/column -->\n\n<!-- wp:wd\/column {\"blockId\":\"927ebcc1-229c-4968-9685-ae79894782c5\",\"adjacentCount\":4,\"adjacentCountTablet\":1,\"adjacentCountMobile\":2,\"colWidthTablet\":100,\"colWidthMobile\":50} -->\n<div id=\"wd-927ebcc1\" class=\"wp-block-wd-column\"><!-- wp:wd\/infobox {\"blockId\":\"47ffe8bc-ccd4-4532-8f92-f03e7fe83c43\",\"align\":\"center\"} -->\n<div id=\"wd-47ffe8bc\" class=\"wp-block-wd-infobox wd-hover-parent wd-align wd-icon-top\"><!-- wp:wd\/icon {\"blockId\":\"f2f37439-668a-42a8-9fd9-daebe47f073d\",\"image\":{\"id\":380,\"url\":\"http:\/\/dummy.xtemos.com\/woodmart2\/megamarket-gutenberg\/wp-content\/uploads\/sites\/25\/2024\/07\/product-quality.svg\"},\"width\":\"32\"} -->\n<div id=\"wd-f2f37439\" class=\"wp-block-wd-icon\"><img class=\"wp-image-380\" src=\"http:\/\/dummy.xtemos.com\/woodmart2\/megamarket-gutenberg\/wp-content\/uploads\/sites\/25\/2024\/07\/product-quality.svg\" alt=\"\" \/><\/div>\n<!-- \/wp:wd\/icon -->\n\n<!-- wp:wd\/container {\"blockId\":\"fcbbe828-949e-45a9-9d3e-f8c1bdf31990\",\"metadata\":{\"name\":\"Infobox content\"}} -->\n<div id=\"wd-fcbbe828\" class=\"wp-block-wd-container wd-dir-col\"><!-- wp:wd\/title {\"blockId\":\"a5ab481b-a416-49a3-9f4c-c5c589cde937\",\"content\":\"Fast Shipping\",\"tpFontSize\":\"16\"} -->\n<h2 id=\"wd-a5ab481b\" class=\"wp-block-wd-title title\">Fast Shipping<\/h2>\n<!-- \/wp:wd\/title -->\n\n<!-- wp:wd\/paragraph {\"blockId\":\"42caca53-7b5e-4bfe-84c1-826bc8c50b65\",\"tpFontSize\":\"14\"} -->\n<p id=\"wd-42caca53\" class=\"wp-block-wd-paragraph\">Track or off orders<\/p>\n<!-- \/wp:wd\/paragraph --><\/div>\n<!-- \/wp:wd\/container --><\/div>\n<!-- \/wp:wd\/infobox --><\/div>\n<!-- \/wp:wd\/column --><\/div>\n<!-- \/wp:wd\/row --><\/div>\n<!-- \/wp:wd\/column --><\/div>\n<!-- \/wp:wd\/row -->\n\n<!-- wp:wd\/sp-tabs {\"blockId\":\"e195f2bc-5595-4f26-9daf-45439dd89bf2\",\"layout\":\"all-open\",\"enableDescription\":false,\"allOpenStyle\":\"overline\",\"additionalInfoColumnGap\":60,\"reviewsLayout\":\"two-column\",\"reviewsColumns\":2,\"allOpenTitleTextTpFontSize\":\"22\",\"marginBottom\":\"60\",\"additionalInfoColumnGapTablet\":30,\"allOpenTitleTextTpFontSizeMobile\":\"20\",\"marginBottomTablet\":\"40\"} \/-->\n\n<!-- wp:wd\/title {\"blockId\":\"8f7433a4-4c56-43d6-a1c6-55563ddc4ba4\",\"design\":\"overlined\",\"content\":\"Description\",\"tpFontSize\":\"22\",\"tpTextDecorationColorVariable\":\"u002du002dwd-primary-color\",\"tpTextDecorationThickness\":\"3\",\"activeBorderColorVariable\":\"\\u002d\\u002dwd-primary-color\"} -->\n<h2 id=\"wd-8f7433a4\" class=\"wp-block-wd-title title wd-design-overlined\"><span>Description<\/span><\/h2>\n<!-- \/wp:wd\/title -->\n\n<!-- wp:wd\/sp-content {\"blockId\":\"95271ebb-d29d-4fa7-bd90-4f928bd4011d\"} \/-->\n\n<!-- wp:wd\/products {\"blockId\":\"4a4f17c8-c181-455e-9d74-682f621cb2d9\",\"show_title\":true,\"layout\":\"carousel\",\"items_per_page\":\"6\",\"product_hover\":\"small\",\"img_size\":\"custom\",\"imgSizeCustomWidth\":\"80\",\"imgSizeCustomHeight\":\"80\",\"products_bordered_grid\":true,\"grid_gallery\":\"no\",\"marginTop\":\"80\",\"slides_per_view\":\"5\",\"hide_pagination_control\":true,\"sync_parent_id\":\"wd_0ba5b2b9\",\"marginTopTablet\":\"60\",\"marginTopMobile\":\"30\",\"slides_per_viewMobile\":\"1\",\"hide_pagination_controlTablet\":true,\"hide_pagination_controlMobile\":true} -->\n<!-- wp:wd\/title {\"blockId\":\"5a122745-d1f0-4f3e-a587-23a3009c6f33\",\"content\":\"Recently Viewed Products\",\"tpFontSize\":\"22\",\"tpFontSizeTablet\":\"22\",\"tpFontSizeMobile\":\"20\"} -->\n<h2 id=\"wd-5a122745\" class=\"wp-block-wd-title title\">Recently Viewed Products<\/h2>\n<!-- \/wp:wd\/title -->\n<!-- \/wp:wd\/products -->"
]